{
  "name": "Erode",
  "panchayats": [
    {
      "name": "Erode",
      "villages": [
        "Erode",
        "Karai Ellapalayam",
        "Elavamalai",
        "Perodu",
        "Nochipalayam",
        "Gangapuram",
        "Ellapalayam",
        "Villarasampatti",
        "Kadirampatti",
        "Rayapalayam",
        "Moolakarai",
        "Koorapalayam",
        "Thottani",
        "Puthur Pudupalayam ",
        "Nanjanapuram",
        "Pavalathampalayam",
        "Veppampalayam",
        "Muthampalayam",
        "Nanjailakkapuram",
        "Punjailakkapuram",
        "Pudur",
        "Thuyyampoondurai ",
        "Kanagapuram",
        "Velampalayam",
        "Punduraisemur",
        "Avalpoondurai ",
        "Modavandi Sathyamangalam",
        "Nanjaiuthukuli ",
        "Kangayampalayam",
        "Sathambur",
        "Nanjaikalamangalam",
        "Punjai Kalamangalam ",
        "Injampalli            ",
        "Thanathampalayam",
        "Elumathur ",
        "Mukasi Hanuman Palli",
        "Attavanai Hanuman Palli",
        "Kagam",
        "Kulavilakku",
        "Palamangalam",
        "Nanjaikolanalli",
        "Kolathupalayam",
        "Kondalam",
        "Ellaikadai",
        "Vilakethi",
        "Kongudayampalayam",
        "Murungiyampalayam",
        "Anjur",
        "Vallipuram",
        "Ichipalayam",
        "Vadivullamangalam",
        "Ayyampalayam",
        "Elunoothimangalam",
        "Devakiammapuram",
        "Avudayaparai",
        "Nagamanaickenpalayam",
        "Mettunasuvanpalayam (CT)",
        "Thindal (CT)"
      ]
    },
    {
      "name": "Sathyamangalam",
      "villages": [
        "Sathyamangalam",
        "Arulavadi",
        "Mallankuli",
        "Dhoddahajanur",
        "Chikkahajanur",
        "Talavadi",
        "Marur",
        "Iggalore",
        "Thingalur ",
        "Koothampalayam",
        "Gundri",
        "Guthiyalathur",
        "Hassanur",
        "Neithalapuram",
        "Thiginarai",
        "Karalavadi",
        "Madahalli",
        "Byannapuram",
        "Panahahalli",
        "Erahanahalli",
        "Dhoddamudukkarai",
        "Gettavadi",
        "Kongahalli",
        "Talamalai",
        "Dasaripalayam",
        "Chikkarasampalayam",
        "Pattavarthiayyampalayam",
        "Rajan Nagar",
        "Pudupeerkadavu",
        "Pungar ",
        "Kothamangalam",
        "Ikkaraithathapalli",
        "Baguthampalayam",
        "Ikkarainegamam",
        "Komarapalayam",
        "Malayadipudur",
        "Alathucombai",
        "Sadumugai",
        "Konamoolai",
        "Akkarainegamam",
        "Boosaripalayam",
        "Akkaraithathappalli",
        "Dhoddampalayam",
        "Thoppampalayam  ",
        "Karidoddampalayam",
        "Shenbagapudur",
        "Indiampalayam",
        "Makkinancombai",
        "Arasur",
        "Ukkaram",
        "Vinnappalli",
        "Kurumbapalayam",
        "Ayyampalayam",
        "Periyakallipatti",
        "Panayampalli",
        "Sunkakaranpalayam",
        "Pungampalli",
        "Thatchaperumapalayam",
        "Sellapampalayam",
        "Nallur",
        "Marayeepalayam ",
        "Madampalayam",
        "Punjaipuliampatti  ",
        "Karapadi",
        "Kavilipalayam",
        "Varapalayam",
        "Mudukkanthurai",
        "Talamalai R.F.",
        "Guthiyalathur Extension  RF",
        "Ullepalayam (R.F.)",
        "Guthiyalathur (Addition) R.F.",
        "Akkurinjieri Extn. R.F.",
        "Akkurinjieri R.F.",
        "Talamalai Extn.(R.F.)",
        "Barabetta RF",
        "Velamundi(R.F.)"
      ]
    },
    {
      "name": "Bhavani",
      "villages": [
        "Bhavani",
        "Burgur",
        "Komarayanur",
        "Pudur",
        "Chennampatti",
        "Ennamangalam",
        "Sankarapalayam",
        "Anthiyur ",
        "Nagalur",
        "Kuppandampalayam",
        "Brammadesam",
        "Pachampalayam  ",
        "Gettisamudram",
        "Mathur",
        "Vellithiruppur",
        "Illippili",
        "Kannapalli",
        "Attavanaipudur",
        "Mukasipudur",
        "Patlur",
        "Oddapalayam",
        "Paruvachi",
        "Vembathi",
        "Moongilpatti",
        "Kilwani",
        "Kuthampoondi",
        "Punnam",
        "Mylambadi",
        "Kalpavi",
        "Kurichi ",
        "Poonachi",
        "Boothapadi",
        "Singampettai",
        "Padavalkalvai",
        "Kadappanallur",
        "Kesarimangalam",
        "Sanyasipatti",
        "Varadanallur",
        "Thalakulam",
        "Bhavani ",
        "Oricheri",
        "Vyramangalam",
        "Alathur",
        "Kavandapadi",
        "Odathurai",
        "Andikulam",
        "Chinnapuliyur",
        "Periyapuliyur",
        "Settipalayam",
        "Burgur (North R.F.)",
        "Thamarakkarai R.F.",
        "Burgur South R.F..",
        "Ennamangalam R.F.",
        "Nagalur R.F.",
        "Kuruppanaickenpalayam (CT)"
      ]
    },
    {
      "name": "Gobichettipalayam",
      "villages": [
        "Gobichettipalayam",
        "Pullappanaickenpalayam",
        "Arrakkankottaigramam",
        "Kongarpalayam",
        "Kavandampalayam",
        "Punjaithuraipalayam",
        "Kondayampalayam",
        "Kanakampalayam",
        "Perumugai",
        "Savandapur",
        "Ammapalayam",
        "Mevani",
        "Perundalaiyur",
        "Kugalur ",
        "Puthukkarai",
        "Palayapariyurkarai",
        "Agraharakarai",
        "Nanjaithuraiampalayam",
        "NanjaiPuliampatti",
        "Bodichinnampalayam",
        "Solamadevikarai",
        "Akkaraikodiveri",
        "Singiripalayam",
        "Alukuli",
        "Pariyur",
        "Vellalapalayam",
        "Nanjaigopi",
        "Pulavakalipalayam",
        "Kullampalayam",
        "Nathipalayam",
        "Modachur  ",
        "Kalingiyam",
        "Kottupullampalayam",
        "Karattupalayam",
        "Odayagoundanpalayam",
        "Kadathur",
        "Sundakkampalayam",
        "Gudakkarai",
        "Andipalayam",
        "Kurumandur",
        "Ayalur",
        "Nagadevampalayam",
        "Kadukkampalayam",
        "Chandrapuram",
        "Vellankovil",
        "Siruvalur",
        "Talguni",
        "Koshanam",
        "Irugalur",
        "Anjanur",
        "Lagampalayam",
        "Vemandampalayam",
        "Polavapalayam",
        "Mottanam",
        "Emmampoondi",
        "Olalakovil",
        "Kadasellipalayam",
        "Sinnaripalayam",
        "Santhipalayam",
        "Avalampalayam",
        "Nichampalayam"
      ]
    },
    {
      "name": "Perundurai",
      "villages": [
        "Perundurai",
        "Thoranavavi",
        "Madathupalayam",
        "Vettaiankinar",
        "Sungakarampalayam",
        "Thingalur",
        "Karukkapalayam",
        "Nichampalayam",
        "Pandiampalayam",
        "Singanallur",
        "Olapalayam",
        "Mullampatti",
        "Kandampalayam",
        "Periyavilamalai",
        "Sinnavilamalai",
        "Thiruvachi",
        "Poovampalayam",
        "Palakarai",
        "Chinnamallampalayam",
        "Nimittipalayam",
        "Unjapalayam",
        "Kallakulam",
        "Sellappampalayam",
        "Talayampalayam",
        "Polanaickampalayam",
        "Karandipalayam",
        "Pappampalayam",
        "Chinnavirasangili",
        "Periyaveerasangili",
        "Marappanaickampalayam",
        "Moongilpalayam",
        "Mettupudur",
        "Ayegoundanpalayam",
        "Seenapuram",
        "Thuduppathi",
        "Sullipalayam",
        "Pattackarampalayam",
        "Kullampalayam",
        "Ponmudi",
        "Vadamugam Vellode ",
        "Pungampadi",
        "Kavundachipalayam",
        "Thenmugam Vellode",
        "Mukasi Pulavapalayam",
        "Ingur",
        "Kambiliampatti",
        "Varapalayam",
        "Kongampalayam",
        "Sirukkalanchi",
        "Kuthampalayam",
        "Voipadi",
        "Chennimalai  ",
        "Murungatholuvu",
        "Pudupalayam    .",
        "Nanjai Palatholuvu",
        "Punjai Palatholuvu",
        "Kodumanal",
        "Orathupalayam",
        "Ellaigramam",
        "Ekkattampalayam",
        "Basuvapatti",
        "Kuppuchipalayam",
        "Chennimalai R.F.",
        "Vijayapuri (CT)",
        "Mukasipidariyur (CT)",
        "Ottapparai (CT)"
      ]
    }
  ]
}